quick_key/__init__.py
quick_key/exceptions.py
quick_key/key.py
quick_key/py.typed
unix_quick_key-0.1.0.dist-info/METADATA
unix_quick_key-0.1.0.dist-info/WHEEL
unix_quick_key-0.1.0.dist-info/licenses/LICENSE
unix_quick_key-0.1.0.dist-info/RECORD
