Metadata-Version: 2.4
Name: unix-quick-key
Version: 0.1.0
Summary: Easy keypress reads
Project-URL: Homepage, https://github.com/GeorgeBannister/python_quick_key
Maintainer-email: GeorgeBannister <gbannister206@gmail.com>
License: MIT License
License-File: LICENSE
Classifier: Operating System :: Unix
Requires-Python: >=3.10
